packageconnector/__init__.py
connectorrrr-0.0.1.dist-info/METADATA
connectorrrr-0.0.1.dist-info/WHEEL
connectorrrr-0.0.1.dist-info/top_level.txt
connectorrrr-0.0.1.dist-info/RECORD
